ansible_mdgen-0.1.1.data/scripts/ansible-mdgen
ansiblemdgen/AnsibleMdgenClient.py
ansiblemdgen/AutoDocumenter.py
ansiblemdgen/AutoDocumenterAppendix.py
ansiblemdgen/AutoDocumenterBase.py
ansiblemdgen/AutoDocumenterFilesTemplates.py
ansiblemdgen/AutoDocumenterIndex.py
ansiblemdgen/AutoDocumenterTasks.py
ansiblemdgen/AutoDocumenterVariables.py
ansiblemdgen/Config.py
ansiblemdgen/Utils.py
ansiblemdgen/__init__.py
ansible_mdgen-0.1.1.dist-info/LICENSE
ansible_mdgen-0.1.1.dist-info/METADATA
ansible_mdgen-0.1.1.dist-info/WHEEL
ansible_mdgen-0.1.1.dist-info/top_level.txt
ansible_mdgen-0.1.1.dist-info/RECORD
