Metadata-Version: 2.1
Name: ansible-mdgen
Version: 0.1.1
Summary: A python package to automate documentation generation for ansible roles.
Home-page: https://github.com/murphypetercl/ansible-mdgen
Author: Peter Murphy
Author-email: murphy.petercl@gmail.com
Classifier: Programming Language :: Python :: 3
Classifier: License :: OSI Approved :: MIT License
Classifier: Operating System :: OS Independent
Requires-Python: >=3.6
License-File: LICENSE
Requires-Dist: pyyaml
Requires-Dist: mdutils
